lichessbotpoetry/__init__.py
lichessbotpoetry/api/__init__.py
lichessbotpoetry/bot/__init__.py
lichessbotpoetry/util.py
lichessbotpoetry-0.1.0.dist-info/WHEEL
lichessbotpoetry-0.1.0.dist-info/METADATA
lichessbotpoetry-0.1.0.dist-info/RECORD
