Metadata-Version: 2.1
Name: lichessbotpoetry
Version: 0.1.0
Summary: 
Author: pythonideas
Author-email: rustbotchessapp@gmail.com
Requires-Python: >=3.8,<4.0
Classifier: Programming Language :: Python :: 3
Classifier: Programming Language :: Python :: 3.8
Classifier: Programming Language :: Python :: 3.9
Requires-Dist: aiohttp (>=3.7.3,<4.0.0)
Requires-Dist: asyncio (>=3.4.3,<4.0.0)
Requires-Dist: python-chess (>=1.999,<2.0)
